Mytestdemo.py
chinesenamewangjing2023-0.0.7.dist-info/LICENSE
chinesenamewangjing2023-0.0.7.dist-info/METADATA
chinesenamewangjing2023-0.0.7.dist-info/WHEEL
chinesenamewangjing2023-0.0.7.dist-info/top_level.txt
chinesenamewangjing2023-0.0.7.dist-info/RECORD
