Metadata-Version: 2.1
Name: chinesenamewangjing2023
Version: 0.0.7
Summary: get a chinesename by random
Home-page: https://github.com/mouday/chinesename
Author: wj
Author-email: 120551025@qq.com
License: License
License-File: LICENSE
